modcloud/__init__.py
modcloud/bigquery.py
modcloud/compute.py
modcloud/dataproc.py
modcloud/period_query_executor.py
modcloud/storage.py
modlog/__init__.py
modlog/bootstrap.py
modlog/decorators.py
modlog/handlers.py
modredis/__init__.py
modredis/modredis.py
modsolr/__init__.py
modsolr/document.py
modsolr/solr.py
modweed/__init__.py
modweed/seaweed.py
modus_facade-0.23.7.dist-info/LICENSE
modus_facade-0.23.7.dist-info/METADATA
modus_facade-0.23.7.dist-info/WHEEL
modus_facade-0.23.7.dist-info/top_level.txt
modus_facade-0.23.7.dist-info/RECORD
