Metadata-Version: 2.1
Name: modus-facade
Version: 0.23.7
Summary: Modus Facade
Home-page: https://github.com/dotmodus/facade
Author: DotModus
Author-email: developers@dotmodus.com
License: UNKNOWN
Platform: UNKNOWN
Classifier: Programming Language :: Python :: 3
Classifier: License :: OSI Approved :: MIT License
Classifier: Operating System :: OS Independent
Requires-Python: >=3.6
Requires-Dist: google-api-python-client (~=1.12.8)
Requires-Dist: google-cloud-storage (~=1.30.0)
Requires-Dist: google-cloud-bigquery (~=2.10.0)
Requires-Dist: oauth2client (~=4.1.3)
Requires-Dist: humanize
Requires-Dist: requests
Requires-Dist: simplejson
Requires-Dist: pytz
Provides-Extra: dev
Requires-Dist: unittest2 ; extra == 'dev'
Requires-Dist: vcrpy ; extra == 'dev'
Requires-Dist: pytest ; extra == 'dev'
Requires-Dist: coverage ; extra == 'dev'
Requires-Dist: codacy-coverage ; extra == 'dev'
Requires-Dist: requests-mock ; extra == 'dev'
Requires-Dist: psutil ; extra == 'dev'
Provides-Extra: mod_redis
Requires-Dist: redis ; extra == 'mod_redis'
